{"sections":{"main":{"type":"main-product-left-thumbs","blocks":{"2e8c7c14-a0ad-4930-a1d8-3def05310426":{"type":"breadcrumb","disabled":true,"settings":{"breadcrumb_layout":"full","breadcrumb_alignment":"left","breadcrumb_bg":"","breadcrumb_gradient":"","breadcrumb_bg_mb":"#f6f6f6","breadcrumb_gradient_mb":"","breadcrumb_mg_top_desktop":30,"breadcrumb_mg_top_mobile":0,"breadcrumb_mg_bottom_desktop":20,"breadcrumb_mg_bottom_mobile":0}},"b0ea69b7-8a54-4a3c-9abd-0fcceeabaaa0":{"type":"title","settings":{"fontsize_text":20,"fontsize_text_mb":14,"color_title":"#232323","spacing_top":0,"spacing_bottom":10}},"4f95b592-8369-4ab0-b30d-24e463fb6890":{"type":"price","settings":{"fontsize_text":18,"spacing_top":0,"spacing_bottom":0}},"judge_me_reviews_preview_badge_H7KGPQ":{"type":"shopify:\/\/apps\/judge-me-reviews\/blocks\/preview_badge\/61ccd3b1-a9f2-4160-9fe9-4fec8413e5d8","settings":{}},"d98e243b-3682-495a-965a-1c7f7d460880":{"type":"variant_picker","settings":{"picker_type":"button","show_variant_image_group":false,"enable_border_top":false,"enable_border_bottom":false,"color_border":"#e6e6e6","spacing_top":12,"spacing_bottom":0}},"04ea8843-f461-4f1d-8ea4-43f62fdfb21e":{"type":"perks","settings":{"spacing_top":0,"spacing_bottom":0,"show_size_chart":true,"size_chart_type":"category_size","size_chart_page":"","size_chart_image_type":"jpg","show_compare_color":false,"show_compare_color_drop_drap":true,"compare_layout":"2"}},"f1b31d90-1e43-4948-9fe3-97ba43f6fb34":{"type":"buy_buttons","settings":{"show_dynamic_checkout":false,"show_gift_card_recipient":false,"spacing_top":10,"spacing_bottom":15,"atc_animation":"none","atc_color":"#ffffff","atc_border_color":"#232323","atc_bg_color":"#232323","atc_bg_color_gradient":"","atc_color_hover":"#232323","atc_border_color_hover":"#232323","atc_bg_color_hover":"#ffffff","atc_bg_color_gradient_hover":"","bin_color":"#232323","bin_border_color":"#acacac","bin_bg_color":"#ffffff","bin_bg_color_gradient":"","bin_color_hover":"#ffffff","bin_border_color_hover":"#232323","bin_bg_color_hover":"#232323","bin_bg_color_hover_gradient":""}},"delivery_time_g8hP6Q":{"type":"delivery_time","settings":{"delivery_time_icon":"1","delivery_time_icon_size":24,"color_title":"#232323","txt":"Order today, get it  [date_start] -[date_end]","fontsize_text":14,"d_start":14,"d_end":20,"exclude_day_from":"only_delivery","exclude_day":"","frm_day":"MMM.DD","time":"16:00:00","hr":"hours","min":"minutes","spacing_top":0,"spacing_bottom":0}},"19de9abb-17c8-4d67-941d-b32706ed06fd":{"type":"pickup_availability","settings":{"show_pickup_availability":true,"spacing_top":0,"spacing_bottom":25}},"bd066b80-c8e3-4f3e-8280-b27fbf6e9423":{"type":"description","settings":{"open_tab_mobile":false,"title":"Product Details","enable_btn_show_more":false,"maximum_des_to_show":300}},"3d9ea84d-5527-4bce-abe6-5debef3ec955":{"type":"custom","settings":{"open_tab_mobile":false,"title":"Shipping & Return","type":"all","content":"<b>Total Delivery Time = Processing Time + Shipping Time<\/b><br>\n<b>Processing Time<\/b>: All normal product will need 12-15 days to process.<br>\n<b>Standard Shipping<\/b>:  5-10 days <br>\n<b>Expedited Shipping<\/b>:  3-6 days <br>\n<br>If you would like to return or exchange the product, please contact us within 14 days of delivery. More details <a href=\"\/pages\/returns-refund\" target=\"_blank\" rel=\"noopener noreferrer\" style=\"font-weight: bold;text-decoration: underline;\">return policy<\/a>.","enable_btn_show_more":false,"maximum_des_to_show":300,"product_custom_source":"dynamic","product_tab_key_metafield":""}},"19ab1d9f-74b2-4c76-bf2e-1bc749e5c2a3":{"type":"share","settings":{"show_share":false,"share_layout":"1","spacing_top":0,"spacing_bottom":0}}},"block_order":["2e8c7c14-a0ad-4930-a1d8-3def05310426","b0ea69b7-8a54-4a3c-9abd-0fcceeabaaa0","4f95b592-8369-4ab0-b30d-24e463fb6890","judge_me_reviews_preview_badge_H7KGPQ","d98e243b-3682-495a-965a-1c7f7d460880","04ea8843-f461-4f1d-8ea4-43f62fdfb21e","f1b31d90-1e43-4948-9fe3-97ba43f6fb34","delivery_time_g8hP6Q","19de9abb-17c8-4d67-941d-b32706ed06fd","bd066b80-c8e3-4f3e-8280-b27fbf6e9423","3d9ea84d-5527-4bce-abe6-5debef3ec955","19ab1d9f-74b2-4c76-bf2e-1bc749e5c2a3"],"settings":{"container":"fullwidth","padding_full_width":0,"show_sticky_info":true,"mg_top_desktop":0,"mg_top_tablet":0,"mg_top_mobile":0,"mg_bottom_desktop":0,"mg_bottom_tablet":0,"mg_bottom_mobile":0,"main_image_arrows_desktop":true,"main_image_arrows_mobile":true,"main_image_counter_mobile":true,"main_image_enable_parallax_mb":false,"main_image_show_zoom_icon_mb":false,"main_image_position":"left","main_image_layout":"1","main_image_show_custom_cursor":false,"count_color":"#191919","icon_color":"#000000","show_thumbnail_mobile":false,"thumnail_layout":"1","thumbnail_to_show":6,"show_sidebar":false,"sidebar_collapse":"collapse","enable_sticky":false,"sidebar_layout":"layout_1","sidebar_collapse_default":"expand","sidebar_position":"left","sidebar_heading_font":"font_1","sidebar_heading_font_size":14,"sidebar_heading_font_weight":"700","sidebar_heading_text_transform":"uppercase","product_image_ratio":"portrait","portrait_aspect_ratio":148,"zoomed_image":true,"media_fit":"unset","product_image_popup":"fancybox","video_layout":"thumbnail","show_badge":true,"show_qty":true,"show_subtotal":true,"subtotal_style":"1","show_sticky_add_to_cart":false,"enable_sticky_add_to_cart_always_mobile":false,"show_sticky_vendor":false,"sticky_atc_layout":"1","show_tab":true,"tab_layout":"vertical","tab_layout_mobile":"vertical","icon_style_layout":"style_1","title_font_size":16,"title_font_size_mb":14,"font_weight_title":"600","title_text_transform":"none","title_padding_top_bottom":15,"tab_border_color":"#000000","tab_border_color_rgb":"","show_product_bundle":true,"background_color":"#f8f8f8","padding_top":30,"padding_top_tablet":30,"padding_top_mobile":30,"padding_bottom":70,"padding_bottom_tablet":40,"padding_bottom_mobile":30,"block_title":"Frequenly Bought Together","block_title_align":"center","block_dots":false,"block_arrows":true,"product_style":"2","block_image_ratio":"adapt","bundle_discount":true,"bundle_discount_text":"Get a [discount]% discount buying these products together","bundle_discount_text_color":"#232323","total_btn_color":"#ffffff","total_btn_border":"#000000","total_btn_bg":"#000000","total_btn_bg_gradient":"","total_btn_color_hover":"#ffffff","total_btn_border_hover":"#d12442","total_btn_bg_hover":"#d12442","total_btn_bg_gradient_hover":""}},"product-recommendations":{"type":"product-recommendations","settings":{"display_product_block":true,"product_block_container":"1170","padding_full_width":0,"enable_border_top":true,"enable_border_bottom":true,"color_border_bottom":"#FFFFFF","border_style":"container","mg_top_desktop":50,"mg_top_tablet":35,"mg_top_mobile":35,"mg_bottom_desktop":20,"mg_bottom_tablet":0,"mg_bottom_mobile":10,"product_block_layout":"slider","product_bg":"#ffffff","style_block_header":"style1","product_block_title":"YOU MAY ALSO LIKE","enable_border_title":true,"mg_top_title":30,"mg_bottom_title":5,"fontsize_title":18,"fontsize_title_mb":16,"color_title":"#232323","border_color_title":"#232323","product_block_title_align":"center","product_block_limit":15,"grid_gap":30,"product_block_per_row":"4","product_block_swipe_on_mobile":true,"product_block_dots":false,"product_block_dots_mb":true,"product_block_arrows":true,"product_block_arrows_mb":false,"product_block_show":"4","product_block_per_view":"4","show_half":true,"scroll_height":4,"scroll_track_bg":"#f1f1f1","scroll_thumb_color":"#000000","scroll_thumb_hover_color":"#444444","enable_hover_drag_icon":true,"enable_layout_special":false,"bg_card":"#ffffff","padding_card":15,"border_radius_card":5,"border_layout_card":"full","border_width_card":5,"border_color_card":"#f0f1f4"}},"1731396807d777f7db":{"type":"apps","blocks":{"judge_me_reviews_review_widget_iwgYC6":{"type":"shopify:\/\/apps\/judge-me-reviews\/blocks\/review_widget\/61ccd3b1-a9f2-4160-9fe9-4fec8413e5d8","settings":{}}},"block_order":["judge_me_reviews_review_widget_iwgYC6"],"settings":{"include_margins":true,"container":"1170"}},"product_block_TzjxMd":{"type":"product-block","settings":{"container":"container","padding_full_width":0,"disable_padding_content":false,"enable_border_top":false,"enable_border_bottom":false,"border_height":1,"color_border_bottom":"#e8e8e8","enable_minus_mg_top":false,"minus_spacing_top":-100,"product_block_layout":"grid","product_bg":"#ffffff","product_bg_gradient":"","style_block_header":"style1","pd_top_title":30,"product_block_title":"BEST SELLERS","enable_border_title":true,"enable_border_title_style2":true,"fontsize_title":16,"fontsize_title_mb":16,"mg_bottom_title":12,"mg_bottom_title_mb":12,"border_color_title":"#232323","color_title":"#232323","view_all":"","view_all_align":"center","font_weight_view_all":"400","mg_bottom_view":30,"mg_bottom_view_mb":0,"enable_border_view_all":true,"link_view_all":"","color_view_all":"#3c3c3c","icon_view_all":"","color_view_all_icon":"#eb492f","title_align":"center","button_text":"Show More","button_text_font_size":14,"button_text_font_weight":"500","button_text_text_transform":"uppercase","product_button_width":270,"pd_top_product_button":12,"pd_bottom_product_button":12,"button_icon":"","mg_bottom_button":55,"enable_button_shadow":false,"color_button":"#ffffff","border_color_button":"#232323","bg_color_button":"#232323","bg_color_gradient_button":"","color_button_hover":"","border_color_button_hover":"","bg_color_button_hover":"","bg_color_gradient_button_hover":"","product_block_collection":"prom-dresses","product_block_limit":8,"grid_gap":30,"pb_style":"style1","style_countdown":"style_1","countdown":"","font_size_countdown_text":14,"color_countdown":"#f42b23","countdown_margin_left":15,"product_block_per_row":"4","product_block_infinite_scroll":true,"product_block_swipe_on_mobile":false,"enable_product_card_pd_bottom":false,"product_card_pd_bottom":40,"product_block_dots":false,"product_block_dots_mb":true,"spacing_top_dots":0,"product_block_arrows":true,"product_block_arrows_mb":false,"product_block_progress_bar":false,"product_block_counter_number":false,"enable_hover_arrow":false,"enable_infinite":true,"product_block_show":"5","position_vertical_arrow":"70px","product_block_per_view":"4","show_half":true,"scroll_height":4,"scroll_track_bg":"#f1f1f1","scroll_thumb_color":"#000000","scroll_thumb_hover_color":"#444444","enable_hover_drag_icon":true,"position":"left","width_banner":40,"display_list_collection":false,"collection_color":"#202020","collection_color_hover":"#3e8cc4","collection_bg_color":"#ffffff","collection_bg_color_gradient":"","text_list":"View all categories","url_list":"","enable_layout_special":false,"bg_card":"#ffffff","padding_card":15,"border_radius_card":5,"border_layout_card":"full","border_width_card":5,"border_color_card":"#f0f1f4","mg_top_desktop":50,"mg_top_tablet":50,"mg_top_mobile":50,"mg_bottom_desktop":50,"mg_bottom_tablet":50,"mg_bottom_mobile":50}},"product-recently-viewed":{"type":"product-recently-viewed","settings":{"display_product_recently_viewed":true,"product_recently_viewed_container":"1170","padding_full_width":0,"enable_border_top":false,"enable_border_bottom":false,"color_border_bottom":"#e8e8e8","border_style":"container","mg_top_desktop":55,"mg_top_tablet":55,"mg_top_mobile":30,"mg_bottom_desktop":0,"mg_bottom_tablet":0,"mg_bottom_mobile":0,"product_recently_viewed_layout":"slider","product_bg":"#ffffff","product_bg_gradient":"","style_block_header":"style1","product_recently_viewed_title":"RECENTLY VIEWED PRODUCTS","enable_border_title":false,"mg_top_title":0,"mg_bottom_title":17,"fontsize_title":22,"fontsize_title_mb":20,"border_color_title":"#232323","color_title":"#232323","product_recently_viewed_title_align":"center","product_recently_viewed_limit":10,"product_recently_viewed_image_ratio":"adapt","grid_gap":30,"product_recently_viewed_per_row":"5","product_recently_viewed_swipe_on_mobile":true,"product_recently_viewed_dots":false,"product_recently_viewed_dots_mb":true,"product_recently_viewed_arrows":true,"product_recently_viewed_arrows_mb":false,"product_recently_viewed_show":"4","product_block_per_view":"4","show_half":true,"scroll_height":4,"scroll_track_bg":"#f1f1f1","scroll_thumb_color":"#000000","scroll_thumb_hover_color":"#444444","enable_hover_drag_icon":true,"enable_layout_special":false,"bg_card":"#ffffff","padding_card":15,"border_radius_card":5,"border_layout_card":"full","border_width_card":5,"border_color_card":"#f0f1f4"}}},"order":["main","product-recommendations","1731396807d777f7db","product_block_TzjxMd","product-recently-viewed"]}